ceos_ard_cli/__init__.py
ceos_ard_cli/compile.py
ceos_ard_cli/generate.py
ceos_ard_cli/schema.py
ceos_ard_cli/validate.py
ceos_ard_cli/version.py
ceos_ard_cli/strictyaml/__init__.py
ceos_ard_cli/strictyaml/id_reference.py
ceos_ard_cli/strictyaml/markdown.py
ceos_ard_cli/strictyaml/md_reference.py
ceos_ard_cli/utils/__init__.py
ceos_ard_cli/utils/files.py
ceos_ard_cli/utils/pfs.py
ceos_ard_cli/utils/requirement.py
ceos_ard_cli/utils/template.py
ceos_ard_cli/utils/yaml.py
ceos_ard_cli-0.2.1.dist-info/METADATA
ceos_ard_cli-0.2.1.dist-info/WHEEL
ceos_ard_cli-0.2.1.dist-info/entry_points.txt
ceos_ard_cli-0.2.1.dist-info/licenses/LICENSE
ceos_ard_cli-0.2.1.dist-info/RECORD
