Metadata-Version: 2.4
Name: ceos-ard-cli
Version: 0.2.1
Summary: CLI tools for CEOS-ARD to generate and validate PFS documents
Project-URL: Homepage, https://github.com/ceos-org/ceos-ard-cli
Project-URL: Repository, https://github.com/ceos-org/ceos-ard-cli
Project-URL: Issues, https://github.com/ceos-org/ceos-ard-cli/issues
Author: Matthias Mohr
License-Expression: Apache-2.0
License-File: LICENSE
Classifier: Development Status :: 4 - Beta
Classifier: License :: OSI Approved :: Apache Software License
Classifier: Programming Language :: Python :: 3
Requires-Python: >=3.9
Requires-Dist: bibtexparser==2.0.0b8
Requires-Dist: click>=8.0.0
Requires-Dist: jinja2>=3.1.0
Requires-Dist: playwright>=1.50.0
Requires-Dist: strictyaml>=1.7.0
Provides-Extra: dev
Requires-Dist: build; extra == 'dev'
Requires-Dist: pre-commit; extra == 'dev'
Requires-Dist: pytest; extra == 'dev'
Requires-Dist: ruff; extra == 'dev'
